__init__.py
dynamicargparse.py
dynamicargparse-1.1.dist-info/LICENSE
dynamicargparse-1.1.dist-info/METADATA
dynamicargparse-1.1.dist-info/WHEEL
dynamicargparse-1.1.dist-info/top_level.txt
dynamicargparse-1.1.dist-info/RECORD
